{"proper":"time", "season":"christmas", "title":"Dec 31, 7th Day Octave", "uri":"christmas/Dec+31,+7th+Day+Octave", "readings":[{"readingType":"ENTRANCE ANTIPHON", "citation":"Is 9:5", "uri":"christmas/Dec+31,+7th+Day+Octave/reading/ENTRANCE+ANTIPHON"}, {"readingType":"1ST", "citation":"1 Jn 2:18-21", "uri":"christmas/Dec+31,+7th+Day+Octave/reading/1ST"}, {"readingType":"PS", "citation":"Ps 96:1-2, 11-12, 13 | resp 11a", "uri":"christmas/Dec+31,+7th+Day+Octave/reading/PS"}, {"readingType":"GA", "citation":"Jn 1:14a, 12a", "uri":"christmas/Dec+31,+7th+Day+Octave/reading/GA"}, {"readingType":"GOSPEL", "citation":"Jn 1:1-18", "uri":"christmas/Dec+31,+7th+Day+Octave/reading/GOSPEL"}, {"readingType":"COMMUNION ANTIPHON", "citation":"1 Jn 4:9", "uri":"christmas/Dec+31,+7th+Day+Octave/reading/COMMUNION+ANTIPHON"}]}